setup.py
royfit/__init__.py
royfit/__version__.py
royfit/core.py
royfit/minimiser.py
royfit.egg-info/PKG-INFO
royfit.egg-info/SOURCES.txt
royfit.egg-info/dependency_links.txt
royfit.egg-info/requires.txt
royfit.egg-info/top_level.txt