Metadata-Version: 1.1
Name: royfit
Version: 0.2
Summary: Restless Oyster Fit - Fast muon reconstruction for KM3NeT
Home-page: http://github.com/tamasgal/royfit/
Author: Tamas Gal
Author-email: tgal@km3net.de
License: UNKNOWN
Platform: any
Classifier: Development Status :: 3 - Alpha
Classifier: Intended Audience :: Developers
Classifier: Intended Audience :: Science/Research
Classifier: Programming Language :: Python
